{
 "generated": "2026-07-24T04:38:08Z",
 "event": "TS Bertha",
 "window": {
  "first": "2026-07-17T15:31:40Z",
  "last": "2026-07-24T04:23:00Z"
 },
 "source": "NOAA NWS/NWPS observed stages via committed gauges-snapshot.json archive; pre-archive window backfilled from USGS/NWPS observed via history.json",
 "gauges": [
  {
   "lid": "SRRT2",
   "name": "San Antonio River at SH 72 near Runge",
   "peak": 34.78,
   "peak_time": "2026-07-19T14:56:00Z",
   "peak_category": "moderate",
   "unit": "ft",
   "first_in_flood": "2026-07-18T03:00:40Z",
   "last_in_flood": "2026-07-20T04:38:00Z",
   "ongoing": false,
   "record": {
    "record_ft": 47.6,
    "record_date": "2016-08-22",
    "peak_pct": 73.1,
    "exceeded": false,
    "approached": false
   },
   "stale": false
  },
  {
   "lid": "FCTT2",
   "name": "Cibolo Creek near Falls City",
   "peak": 23.48,
   "peak_time": "2026-07-18T02:42:54Z",
   "peak_category": "moderate",
   "unit": "ft",
   "first_in_flood": "2026-07-17T15:31:40Z",
   "last_in_flood": "2026-07-18T20:27:00Z",
   "ongoing": false,
   "record": {
    "record_ft": 39.86,
    "record_date": "1998-10-19",
    "peak_pct": 58.9,
    "exceeded": false,
    "approached": false
   },
   "stale": false
  },
  {
   "lid": "GLIT2",
   "name": "San Antonio River at Goliad",
   "peak": 26.29,
   "peak_time": "2026-07-20T21:08:00Z",
   "peak_category": "minor",
   "unit": "ft",
   "first_in_flood": "2026-07-20T05:53:00Z",
   "last_in_flood": "2026-07-21T07:38:00Z",
   "ongoing": false,
   "record": {
    "record_ft": 53.7,
    "record_date": "1967-09-23",
    "peak_pct": 49.0,
    "exceeded": false,
    "approached": false
   },
   "stale": false
  }
 ],
 "skipped_commits": 0
}
